Metadata-Version: 2.1
Name: jft
Version: 0.0.149
Summary: Function Test Pair Toolbox
Home-page: https://gitlab.com/zereiji/jft
Author: @JohnRForbes
Author-email: john.robert.forbes@gmail.com
License: MIT
Keywords: jft
Platform: UNKNOWN
Classifier: Programming Language :: Python :: 3
Classifier: License :: OSI Approved :: MIT License
Classifier: Operating System :: OS Independent
Requires-Python: >=3.7
License-File: LICENSE
